spela/__init__.py
spela/augmentation.py
spela/filterbank.py
spela/melspectrogram.py
spela/normalisation.py
spela/spectrogram.py
utils/__init__.py
utils/backend.py
utils/conv_utils.py
spela-0.0.5.dist-info/METADATA
spela-0.0.5.dist-info/WHEEL
spela-0.0.5.dist-info/top_level.txt
spela-0.0.5.dist-info/RECORD
