Metadata-Version: 2.1
Name: spela
Version: 0.0.5
Summary: spectrogram layers
Home-page: https://github.com/kongkip/spela.git
Author: Evans Kiplagat
Author-email: evanskiplagat3@gmail.com
License: MIT
Platform: UNKNOWN
Requires-Dist: numpy
Requires-Dist: librosa
Requires-Dist: matplotlib
